learnware/__init__.py
learnware/config.py
learnware/logger.py
learnware/client/__init__.py
learnware/client/container.py
learnware/client/learnware_client.py
learnware/client/package_utils.py
learnware/client/utils.py
learnware/client/scripts/__init__.py
learnware/client/scripts/install_env.py
learnware/client/scripts/run_model.py
learnware/learnware/__init__.py
learnware/learnware/base.py
learnware/learnware/utils.py
learnware/market/__init__.py
learnware/market/base.py
learnware/market/classes.py
learnware/market/module.py
learnware/market/utils.py
learnware/market/anchor/__init__.py
learnware/market/anchor/organizer.py
learnware/market/anchor/searcher.py
learnware/market/anchor/user_info.py
learnware/market/easy/__init__.py
learnware/market/easy/checker.py
learnware/market/easy/database_ops.py
learnware/market/easy/organizer.py
learnware/market/easy/searcher.py
learnware/market/evolve/__init__.py
learnware/market/evolve/organizer.py
learnware/market/evolve_anchor/__init__.py
learnware/market/evolve_anchor/organizer.py
learnware/market/heterogeneous/__init__.py
learnware/market/heterogeneous/searcher.py
learnware/market/heterogeneous/utils.py
learnware/market/heterogeneous/organizer/__init__.py
learnware/market/heterogeneous/organizer/hetero_map/__init__.py
learnware/market/heterogeneous/organizer/hetero_map/feature_extractor.py
learnware/market/heterogeneous/organizer/hetero_map/trainer.py
learnware/market/llm/__init__.py
learnware/market/llm/organizer.py
learnware/market/llm/searcher.py
learnware/model/__init__.py
learnware/model/base.py
learnware/model/torch_model.py
learnware/reuse/__init__.py
learnware/reuse/align.py
learnware/reuse/averaging.py
learnware/reuse/base.py
learnware/reuse/ensemble_pruning.py
learnware/reuse/feature_augment.py
learnware/reuse/job_selector.py
learnware/reuse/utils.py
learnware/reuse/hetero/__init__.py
learnware/reuse/hetero/feature_align.py
learnware/reuse/hetero/hetero_map.py
learnware/specification/__init__.py
learnware-0.4.0.post1.dist-info/licenses/LICENSE
learnware-0.4.0.post1.dist-info/METADATA
learnware-0.4.0.post1.dist-info/WHEEL
learnware-0.4.0.post1.dist-info/top_level.txt
learnware-0.4.0.post1.dist-info/RECORD
