Metadata-Version: 2.4
Name: learnware
Version: 0.4.0.post1
Summary: The learnware package supports the submission, usability testing, organization, identification, deployment, and reuse of learnware.
Home-page: https://github.com/Learnware-LAMDA/learnware
License: Apache-2.0 Licence
Classifier: Intended Audience :: Science/Research
Classifier: Intended Audience :: Developers
Classifier: Programming Language :: Python
Classifier: Topic :: Software Development
Classifier: Topic :: Scientific/Engineering
Classifier: Operating System :: POSIX :: Linux
Classifier: Operating System :: Microsoft :: Windows
Classifier: Programming Language :: Python :: 3.8
Classifier: Programming Language :: Python :: 3.9
Classifier: Programming Language :: Python :: 3.10
Classifier: Programming Language :: Python :: 3.11
Requires-Python: >=3.6.0
License-File: LICENSE
Requires-Dist: numpy>=1.20.0
Requires-Dist: pandas>=0.25.1
Requires-Dist: scipy>=1.0.0
Requires-Dist: tqdm>=4.65.0
Requires-Dist: scikit-learn>=0.22
Requires-Dist: joblib>=1.2.0
Requires-Dist: pyyaml>=6.0
Requires-Dist: fire>=0.3.1
Requires-Dist: psutil>=5.9.4
Requires-Dist: sqlalchemy>=2.0.21
Requires-Dist: shortuuid>=1.0.11
Requires-Dist: docker>=6.1.3
Requires-Dist: rapidfuzz>=3.4.0
Requires-Dist: langdetect>=1.0.9
Requires-Dist: huggingface-hub
Requires-Dist: transformers>=4.34.1
Requires-Dist: portalocker>=2.0.0
Requires-Dist: qpsolvers[clarabel]>=4.0.1
Requires-Dist: geatpy>=2.7.0; python_version < "3.11"
Requires-Dist: trl>=0.11.4
Requires-Dist: datasets>=2.16.0
Requires-Dist: peft>=0.13.2
Requires-Dist: lm_eval>=0.4.7
Provides-Extra: dev
Requires-Dist: sphinx; extra == "dev"
Requires-Dist: sphinx_book_theme==0.3.3; extra == "dev"
Requires-Dist: pytest>=3; extra == "dev"
Requires-Dist: wheel; extra == "dev"
Requires-Dist: setuptools; extra == "dev"
Requires-Dist: pylint; extra == "dev"
Requires-Dist: mypy<0.981; extra == "dev"
Requires-Dist: flake8; extra == "dev"
Requires-Dist: black==23.1.0; extra == "dev"
Requires-Dist: pre-commit; extra == "dev"
Provides-Extra: full
Requires-Dist: torch==2.0.1; extra == "full"
Requires-Dist: torchvision==0.15.2; extra == "full"
Requires-Dist: torch-optimizer>=0.3.0; extra == "full"
Requires-Dist: lightgbm>=3.3.0; extra == "full"
Requires-Dist: sentence_transformers==3.2.1; extra == "full"
Requires-Dist: fast_pytorch_kmeans==0.2.0.1; extra == "full"
Dynamic: classifier
Dynamic: description
Dynamic: description-content-type
Dynamic: home-page
Dynamic: license
Dynamic: license-file
Dynamic: provides-extra
Dynamic: requires-dist
Dynamic: requires-python
Dynamic: summary
